utils_tools_for_musesoft/__init__.py
utils_tools_for_musesoft/cli.py
utils_tools_for_musesoft/utils_tools_for_musesoft.py
msutils123-0.1.0.dist-info/AUTHORS.rst
msutils123-0.1.0.dist-info/LICENSE
msutils123-0.1.0.dist-info/METADATA
msutils123-0.1.0.dist-info/WHEEL
msutils123-0.1.0.dist-info/entry_points.txt
msutils123-0.1.0.dist-info/top_level.txt
msutils123-0.1.0.dist-info/RECORD
