Metadata-Version: 2.1
Name: msutils123
Version: 0.1.0
Summary: Utils tools for musesoft
Home-page: https://github.com/mtvu/utils_tools_for_musesoft
Author: Tuan Vu
Author-email: tuanmanh@gmail.com
License: MIT license
Keywords: utils_tools_for_musesoft
Platform: UNKNOWN
Classifier: Development Status :: 2 - Pre-Alpha
Classifier: Intended Audience :: Developers
Classifier: License :: OSI Approved :: MIT License
Classifier: Natural Language :: English
Classifier: Programming Language :: Python :: 2
Classifier: Programming Language :: Python :: 2.7
Classifier: Programming Language :: Python :: 3
Classifier: Programming Language :: Python :: 3.4
Classifier: Programming Language :: Python :: 3.5
Classifier: Programming Language :: Python :: 3.6
Classifier: Programming Language :: Python :: 3.7
Requires-Dist: Click (>=6.0)
